<?xml version="1.0" encoding="utf-8"?><DEFECTS><DEFECT>
    <SFA>
      <FILEPATH>C:\Users\user\source\repos\14\14\</FILEPATH>
      <FILENAME>Source.cpp</FILENAME>
      <LINE>13</LINE>
      <COLUMN>1</COLUMN>
    </SFA>
    <DEFECTCODE>26495</DEFECTCODE>
    <DESCRIPTION>Variable 'Edition::id' is uninitialized. Always initialize a member variable (type.6).</DESCRIPTION>
    <FUNCTION>Edition::{ctor}</FUNCTION>
    <DECORATED>??0Edition@@QAE@XZ</DECORATED>
    <FUNCLINE>13</FUNCLINE>
    <ADDITIONALINFO>
      <targetSymbol>Edition::id</targetSymbol>
    </ADDITIONALINFO>
    <PATH></PATH>
  </DEFECT></DEFECTS>